Lab 3/task6_top.v
module task6_top (
    input wire clock,
    input wire a, b,
    output q, 
    output reg state
);

assign q = a ^ b ^ state;

always @(posedge clock) begin
    state <= b==a ? a : state;
end

endmodule

Lab 3/tesk6_tb.v
`timescale 1ns/100ps // 1 ns time unit, 100 ps resolution

module task6_tb;

reg clk=0;
always #1 clk = !clk;

reg a, b;
wire q, state;

task6_top task6_inst (
    .clock(clk),
    .a(a),
    .b(b),
    .q(q),
    .state(state)
);

initial begin
    $dumpfile("wave.vcd");		// create a VCD waveform dump called "wave.vcd"
    $dumpvars(0, task6_tb);	    // dump variable changes in the testbench and all modules under it

    a <= 0;
    b <= 0;
    #3 b <= 1;
    #2 a <= 1; b <= 0;
    #2 b <= 1;
    #2 a <= 0; b <= 0;
    #2 a <= 1; b <= 1;
    #6 b <= 0;
    #2 a <= 0; b <= 1;
    #2 b <= 0;


    #5 $finish();
end

initial begin
    $monitor("t=%-4d: clock = $d, a = %d, b = %d, q = %d, state = %d" , $time, clk, a, b, q, state);
end

endmodule

Lab 3/out/wave.vcd
$date
	Thu Oct 24 10:35:50 2024
$end
$version
	Icarus Verilog
$end
$timescale
	100ps
$end
$scope module task6_tb $end
$var wire 1 ! state $end
$var wire 1 " q $end
$var reg 1 # a $end
$var reg 1 $ b $end
$var reg 1 % clk $end
$scope module task6_inst $end
$var wire 1 # a $end
$var wire 1 $ b $end
$var wire 1 % clock $end
$var wire 1 " q $end
$var reg 1 ! state $end
$upscope $end
$upscope $end
$enddefinitions $end
$comment Show the parameter values. $end
$dumpall
$end
#0
$dumpvars
0%
0$
0#
x"
x!
$end
#10
0"
0!
1%
#20
0%
#30
1"
1$
1%
#40
0%
#50
0$
1#
1%
#60
0%
#70
0"
1$
1%
#80
0%
#90
1"
1!
0$
0#
1%
#100
0%
#110
0"
0!
1$
1#
1%
#120
0%
#130
1"
1!
1%
#140
0%
#150
1%
#160
0%
#170
0"
0$
1%
#180
0%
#190
1$
0#
1%
#200
0%
#210
1"
0$
1%
#220
0%
#230
0"
0!
1%
