Lab 4/counter.v
module counter (
    input clk,
    input rst,
    output reg [9:0] q
);

always @(posedge clk) begin
    q <= rst == 1 ? 0 : q == 999 ? 0 : q + 1;
end

endmodule

Lab 4/shift_counter.v
module shift_counter (
    input clk,
    input shift_ena,
    input count_ena,
    input data,
    output reg [3:0] q = 0
);

always @(posedge clk) begin
    if(shift_ena) begin 
        q = {q[2:0], data};
    end

    if(count_ena) begin
        q <= q - 1;
    end
end


endmodule

Lab 4/start_detector.v
module start_detector(
    input wire clk,
    input wire rst,
    input wire data,
    output reg start_shifting = 0
);

reg [3:0] buffer = 0;

// always @(posedge clk) begin

//     // if(~start_shifting) begin 
//         buffer = {buffer[2:0], data};
//     // end

//     if(rst) begin 
//         start_shifting <= 0;
//     end 

//     if(buffer == 4'b1101) begin 
//         start_shifting = 1;
//     end 
// end

reg [2:0] state = 0;

always @(posedge clk) begin
    if(state == 0) begin
        if(data == 1) begin 
            state <= 1;
        end
    end
    if(state == 1) begin
        if(data == 1) begin 
            state <= 2;
        end else begin 
            state <= 0;
        end
    end
    if(state == 2) begin
        if(data == 0) begin 
            state <= 3;
        end else begin 
            state <= 0;
        end
    end
    if(state == 3) begin
        if(data == 1) begin 
            state <= 0;
            start_shifting = 1;
        end else begin 
            state <= 0;
        end
    end

    if(rst) begin 
        start_shifting <= 0;
        state = 0;
    end 
end

endmodule

Lab 4/timer.v
module timer (
    input clk,
    input data,
    input rst,
    input ask,
    output reg counting = 0,
    output reg done = 0
);


reg[3:0] state = 0;
wire start_shifting;
reg[2:0] bits_read = 0;
wire[3:0] delay;

// 0 - idle 
// 1 - shifting 
// 2 - master_cnt_loop 
// 3 - slave_cnt_loop
// 4 - done

start_detector trigger (
    .clk(clk),
    .rst(rst),
    .data(data),
    .start_shifting(start_shifting)
);


assign shifting = (state == 1);
assign master_cnt = (state == 2);

shift_counter master_cnt (
    .clk(clk),
    .shift_ena(shifting),
    .count_ena(master_cnt),
    .data(data),
    .q(delay)
);

counter slave_cnt (
    .clk(clk),
    .rst(rst),
    .q()
);

always @(posedge clk) begin

    // display state
    $display("t=%-4d: state = %d, bits_read. = %d, delay = %d, slave_delay = %d, ask = %d", ($time + 1) / 2, state, bits_read, delay, slave_cnt.q, ask);

    if(state == 0) begin // if idle 
        if(start_shifting) begin 
            state <= 1;
            bits_read = 0;
            trigger.start_shifting <= 0;
        end
    end

    if(state == 1) begin 
        bits_read <= bits_read + 1;
        if(bits_read == 3) begin
            state <= 3;
            slave_cnt.q <= 0; 
            counting <= 1;
        end
    end

    if(state == 2) begin
        if(delay == 0) begin
            state <= 4;
            counting <= 0;
            done <= 1;
        end
        else begin
            state <= 3;
            slave_cnt.q <= 0; // set start value for slave timer 
        end
    end

    if(state == 3) begin
        if(slave_cnt.q == 999) begin
            state <= 2;
            slave_cnt.q <= 0; // set start value for slave timer 
        end
    end

    if(state == 4) begin
        if(ask == 1) begin
            state <= 0;
            done <= 0;
        end
    end

end

endmodule

Lab 4/timer_tb.v
`timescale 1ps/1ps

module timer_tb;

reg clk = 0;
always #1 clk = ~clk;

reg data = 0;
reg rst = 0;
reg ask = 0;

wire counting;
wire done;
wire shift_ena;


timer tim(
    .clk(clk),
    .data(data),
    .rst(rst),
    .ask(ask),
    .counting(counting),
    .done(done)
);

initial begin
    $dumpfile("wave.vcd");
    $dumpvars(0, timer_tb);

    data = 0;
    #1 data = 1;
    #2 data = 1;
    #2 data = 0;
    #2 data = 1;


    #2 data = 0;
    #2 data = 0;
    #2 data = 0;
    #2 data = 0;

    #2400 ask = 1;
    #2 ask = 0;

    #100 $finish();
end

always @(posedge clk) begin
    // $display("t=%-4d: data = %d, counting = %d, done = %d, ask = %d", ($time + 1)/ 2, data, counting, done, ask);
end

endmodule

Lab 4/out/wave.vcd
$date
	Sat Nov 16 13:29:17 2024
$end
$version
	Icarus Verilog
$end
$timescale
	1ps
$end
$scope module timer_tb $end
$var wire 1 ! done $end
$var wire 1 " counting $end
$var reg 1 # ask $end
$var reg 1 $ clk $end
$var reg 1 % data $end
$var reg 1 & rst $end
$scope module tim $end
$var wire 1 # ask $end
$var wire 1 $ clk $end
$var wire 1 % data $end
$var wire 1 & rst $end
$var wire 1 ' start_shifting $end
$var wire 1 ( shifting $end
$var wire 1 ) master_cnt $end
$var wire 4 * delay [3:0] $end
$var reg 3 + bits_read [2:0] $end
$var reg 1 " counting $end
$var reg 1 ! done $end
$var reg 4 , state [3:0] $end
$scope module master_cnt $end
$var wire 1 $ clk $end
$var wire 1 ) count_ena $end
$var wire 1 % data $end
$var wire 1 ( shift_ena $end
$var reg 4 - q [3:0] $end
$upscope $end
$scope module slave_cnt $end
$var wire 1 $ clk $end
$var wire 1 & rst $end
$var reg 10 . q [9:0] $end
$upscope $end
$scope module trigger $end
$var wire 1 $ clk $end
$var wire 1 % data $end
$var wire 1 & rst $end
$var reg 4 / buffer [3:0] $end
$var reg 1 ' start_shifting $end
$var reg 3 0 state [2:0] $end
$upscope $end
$upscope $end
$upscope $end
$enddefinitions $end
$comment Show the parameter values. $end
$dumpall
$end
#0
$dumpvars
b0 0
b0 /
bx .
b0 -
b0 ,
b0 +
b0 *
0)
0(
0'
0&
0%
0$
0#
0"
0!
$end
#1
b1 0
1%
1$
#2
0$
#3
b10 0
1$
#4
0$
#5
b11 0
1$
0%
#6
0$
#7
1(
b1 ,
b0 0
0'
1$
1%
#8
0$
#9
b1 +
1$
0%
#10
0$
#11
b10 +
1$
#12
0$
#13
b11 +
1$
#14
0$
#15
1"
b0 .
0(
b11 ,
b100 +
1$
#16
0$
#17
b1 .
1$
#18
0$
#19
b10 .
1$
#20
0$
#21
b11 .
1$
#22
0$
#23
b100 .
1$
#24
0$
#25
b101 .
1$
#26
0$
#27
b110 .
1$
#28
0$
#29
b111 .
1$
#30
0$
#31
b1000 .
1$
#32
0$
#33
b1001 .
1$
#34
0$
#35
b1010 .
1$
#36
0$
#37
b1011 .
1$
#38
0$
#39
b1100 .
1$
#40
0$
#41
b1101 .
1$
#42
0$
#43
b1110 .
1$
#44
0$
#45
b1111 .
1$
#46
0$
#47
b10000 .
1$
#48
0$
#49
b10001 .
1$
#50
0$
#51
b10010 .
1$
#52
0$
#53
b10011 .
1$
#54
0$
#55
b10100 .
1$
#56
0$
#57
b10101 .
1$
#58
0$
#59
b10110 .
1$
#60
0$
#61
b10111 .
1$
#62
0$
#63
b11000 .
1$
#64
0$
#65
b11001 .
1$
#66
0$
#67
b11010 .
1$
#68
0$
#69
b11011 .
1$
#70
0$
#71
b11100 .
1$
#72
0$
#73
b11101 .
1$
#74
0$
#75
b11110 .
1$
#76
0$
#77
b11111 .
1$
#78
0$
#79
b100000 .
1$
#80
0$
#81
b100001 .
1$
#82
0$
#83
b100010 .
1$
#84
0$
#85
b100011 .
1$
#86
0$
#87
b100100 .
1$
#88
0$
#89
b100101 .
1$
#90
0$
#91
b100110 .
1$
#92
0$
#93
b100111 .
1$
#94
0$
#95
b101000 .
1$
#96
0$
#97
b101001 .
1$
#98
0$
#99
b101010 .
1$
#100
0$
#101
b101011 .
1$
#102
0$
#103
b101100 .
1$
#104
0$
#105
b101101 .
1$
#106
0$
#107
b101110 .
1$
#108
0$
#109
b101111 .
1$
#110
0$
#111
b110000 .
1$
#112
0$
#113
b110001 .
1$
#114
0$
#115
b110010 .
1$
#116
0$
#117
b110011 .
1$
#118
0$
#119
b110100 .
1$
#120
0$
#121
b110101 .
1$
#122
0$
#123
b110110 .
1$
#124
0$
#125
b110111 .
1$
#126
0$
#127
b111000 .
1$
#128
0$
#129
b111001 .
1$
#130
0$
#131
b111010 .
1$
#132
0$
#133
b111011 .
1$
#134
0$
#135
b111100 .
1$
#136
0$
#137
b111101 .
1$
#138
0$
#139
b111110 .
1$
#140
0$
#141
b111111 .
1$
#142
0$
#143
b1000000 .
1$
#144
0$
#145
b1000001 .
1$
#146
0$
#147
b1000010 .
1$
#148
0$
#149
b1000011 .
1$
#150
0$
#151
b1000100 .
1$
#152
0$
#153
b1000101 .
1$
#154
0$
#155
b1000110 .
1$
#156
0$
#157
b1000111 .
1$
#158
0$
#159
b1001000 .
1$
#160
0$
#161
b1001001 .
1$
#162
0$
#163
b1001010 .
1$
#164
0$
#165
b1001011 .
1$
#166
0$
#167
b1001100 .
1$
#168
0$
#169
b1001101 .
1$
#170
0$
#171
b1001110 .
1$
#172
0$
#173
b1001111 .
1$
#174
0$
#175
b1010000 .
1$
#176
0$
#177
b1010001 .
1$
#178
0$
#179
b1010010 .
1$
#180
0$
#181
b1010011 .
1$
#182
0$
#183
b1010100 .
1$
#184
0$
#185
b1010101 .
1$
#186
0$
#187
b1010110 .
1$
#188
0$
#189
b1010111 .
1$
#190
0$
#191
b1011000 .
1$
#192
0$
#193
b1011001 .
1$
#194
0$
#195
b1011010 .
1$
#196
0$
#197
b1011011 .
1$
#198
0$
#199
b1011100 .
1$
#200
0$
#201
b1011101 .
1$
#202
0$
#203
b1011110 .
1$
#204
0$
#205
b1011111 .
1$
#206
0$
#207
b1100000 .
1$
#208
0$
#209
b1100001 .
1$
#210
0$
#211
b1100010 .
1$
#212
0$
#213
b1100011 .
1$
#214
0$
#215
b1100100 .
1$
#216
0$
#217
b1100101 .
1$
#218
0$
#219
b1100110 .
1$
#220
0$
#221
b1100111 .
1$
#222
0$
#223
b1101000 .
1$
#224
0$
#225
b1101001 .
1$
#226
0$
#227
b1101010 .
1$
#228
0$
#229
b1101011 .
1$
#230
0$
#231
b1101100 .
1$
#232
0$
#233
b1101101 .
1$
#234
0$
#235
b1101110 .
1$
#236
0$
#237
b1101111 .
1$
#238
0$
#239
b1110000 .
1$
#240
0$
#241
b1110001 .
1$
#242
0$
#243
b1110010 .
1$
#244
0$
#245
b1110011 .
1$
#246
0$
#247
b1110100 .
1$
#248
0$
#249
b1110101 .
1$
#250
0$
#251
b1110110 .
1$
#252
0$
#253
b1110111 .
1$
#254
0$
#255
b1111000 .
1$
#256
0$
#257
b1111001 .
1$
#258
0$
#259
b1111010 .
1$
#260
0$
#261
b1111011 .
1$
#262
0$
#263
b1111100 .
1$
#264
0$
#265
b1111101 .
1$
#266
0$
#267
b1111110 .
1$
#268
0$
#269
b1111111 .
1$
#270
0$
#271
b10000000 .
1$
#272
0$
#273
b10000001 .
1$
#274
0$
#275
b10000010 .
1$
#276
0$
#277
b10000011 .
1$
#278
0$
#279
b10000100 .
1$
#280
0$
#281
b10000101 .
1$
#282
0$
#283
b10000110 .
1$
#284
0$
#285
b10000111 .
1$
#286
0$
#287
b10001000 .
1$
#288
0$
#289
b10001001 .
1$
#290
0$
#291
b10001010 .
1$
#292
0$
#293
b10001011 .
1$
#294
0$
#295
b10001100 .
1$
#296
0$
#297
b10001101 .
1$
#298
0$
#299
b10001110 .
1$
#300
0$
#301
b10001111 .
1$
#302
0$
#303
b10010000 .
1$
#304
0$
#305
b10010001 .
1$
#306
0$
#307
b10010010 .
1$
#308
0$
#309
b10010011 .
1$
#310
0$
#311
b10010100 .
1$
#312
0$
#313
b10010101 .
1$
#314
0$
#315
b10010110 .
1$
#316
0$
#317
b10010111 .
1$
#318
0$
#319
b10011000 .
1$
#320
0$
#321
b10011001 .
1$
#322
0$
#323
b10011010 .
1$
#324
0$
#325
b10011011 .
1$
#326
0$
#327
b10011100 .
1$
#328
0$
#329
b10011101 .
1$
#330
0$
#331
b10011110 .
1$
#332
0$
#333
b10011111 .
1$
#334
0$
#335
b10100000 .
1$
#336
0$
#337
b10100001 .
1$
#338
0$
#339
b10100010 .
1$
#340
0$
#341
b10100011 .
1$
#342
0$
#343
b10100100 .
1$
#344
0$
#345
b10100101 .
1$
#346
0$
#347
b10100110 .
1$
#348
0$
#349
b10100111 .
1$
#350
0$
#351
b10101000 .
1$
#352
0$
#353
b10101001 .
1$
#354
0$
#355
b10101010 .
1$
#356
0$
#357
b10101011 .
1$
#358
0$
#359
b10101100 .
1$
#360
0$
#361
b10101101 .
1$
#362
0$
#363
b10101110 .
1$
#364
0$
#365
b10101111 .
1$
#366
0$
#367
b10110000 .
1$
#368
0$
#369
b10110001 .
1$
#370
0$
#371
b10110010 .
1$
#372
0$
#373
b10110011 .
1$
#374
0$
#375
b10110100 .
1$
#376
0$
#377
b10110101 .
1$
#378
0$
#379
b10110110 .
1$
#380
0$
#381
b10110111 .
1$
#382
0$
#383
b10111000 .
1$
#384
0$
#385
b10111001 .
1$
#386
0$
#387
b10111010 .
1$
#388
0$
#389
b10111011 .
1$
#390
0$
#391
b10111100 .
1$
#392
0$
#393
b10111101 .
1$
#394
0$
#395
b10111110 .
1$
#396
0$
#397
b10111111 .
1$
#398
0$
#399
b11000000 .
1$
#400
0$
#401
b11000001 .
1$
#402
0$
#403
b11000010 .
1$
#404
0$
#405
b11000011 .
1$
#406
0$
#407
b11000100 .
1$
#408
0$
#409
b11000101 .
1$
#410
0$
#411
b11000110 .
1$
#412
0$
#413
b11000111 .
1$
#414
0$
#415
b11001000 .
1$
#416
0$
#417
b11001001 .
1$
#418
0$
#419
b11001010 .
1$
#420
0$
#421
b11001011 .
1$
#422
0$
#423
b11001100 .
1$
#424
0$
#425
b11001101 .
1$
#426
0$
#427
b11001110 .
1$
#428
0$
#429
b11001111 .
1$
#430
0$
#431
b11010000 .
1$
#432
0$
#433
b11010001 .
1$
#434
0$
#435
b11010010 .
1$
#436
0$
#437
b11010011 .
1$
#438
0$
#439
b11010100 .
1$
#440
0$
#441
b11010101 .
1$
#442
0$
#443
b11010110 .
1$
#444
0$
#445
b11010111 .
1$
#446
0$
#447
b11011000 .
1$
#448
0$
#449
b11011001 .
1$
#450
0$
#451
b11011010 .
1$
#452
0$
#453
b11011011 .
1$
#454
0$
#455
b11011100 .
1$
#456
0$
#457
b11011101 .
1$
#458
0$
#459
b11011110 .
1$
#460
0$
#461
b11011111 .
1$
#462
0$
#463
b11100000 .
1$
#464
0$
#465
b11100001 .
1$
#466
0$
#467
b11100010 .
1$
#468
0$
#469
b11100011 .
1$
#470
0$
#471
b11100100 .
1$
#472
0$
#473
b11100101 .
1$
#474
0$
#475
b11100110 .
1$
#476
0$
#477
b11100111 .
1$
#478
0$
#479
b11101000 .
1$
#480
0$
#481
b11101001 .
1$
#482
0$
#483
b11101010 .
1$
#484
0$
#485
b11101011 .
1$
#486
0$
#487
b11101100 .
1$
#488
0$
#489
b11101101 .
1$
#490
0$
#491
b11101110 .
1$
#492
0$
#493
b11101111 .
1$
#494
0$
#495
b11110000 .
1$
#496
0$
#497
b11110001 .
1$
#498
0$
#499
b11110010 .
1$
#500
0$
#501
b11110011 .
1$
#502
0$
#503
b11110100 .
1$
#504
0$
#505
b11110101 .
1$
#506
0$
#507
b11110110 .
1$
#508
0$
#509
b11110111 .
1$
#510
0$
#511
b11111000 .
1$
#512
0$
#513
b11111001 .
1$
#514
0$
#515
b11111010 .
1$
#516
0$
#517
b11111011 .
1$
#518
0$
#519
b11111100 .
1$
#520
0$
#521
b11111101 .
1$
#522
0$
#523
b11111110 .
1$
#524
0$
#525
b11111111 .
1$
#526
0$
#527
b100000000 .
1$
#528
0$
#529
b100000001 .
1$
#530
0$
#531
b100000010 .
1$
#532
0$
#533
b100000011 .
1$
#534
0$
#535
b100000100 .
1$
#536
0$
#537
b100000101 .
1$
#538
0$
#539
b100000110 .
1$
#540
0$
#541
b100000111 .
1$
#542
0$
#543
b100001000 .
1$
#544
0$
#545
b100001001 .
1$
#546
0$
#547
b100001010 .
1$
#548
0$
#549
b100001011 .
1$
#550
0$
#551
b100001100 .
1$
#552
0$
#553
b100001101 .
1$
#554
0$
#555
b100001110 .
1$
#556
0$
#557
b100001111 .
1$
#558
0$
#559
b100010000 .
1$
#560
0$
#561
b100010001 .
1$
#562
0$
#563
b100010010 .
1$
#564
0$
#565
b100010011 .
1$
#566
0$
#567
b100010100 .
1$
#568
0$
#569
b100010101 .
1$
#570
0$
#571
b100010110 .
1$
#572
0$
#573
b100010111 .
1$
#574
0$
#575
b100011000 .
1$
#576
0$
#577
b100011001 .
1$
#578
0$
#579
b100011010 .
1$
#580
0$
#581
b100011011 .
1$
#582
0$
#583
b100011100 .
1$
#584
0$
#585
b100011101 .
1$
#586
0$
#587
b100011110 .
1$
#588
0$
#589
b100011111 .
1$
#590
0$
#591
b100100000 .
1$
#592
0$
#593
b100100001 .
1$
#594
0$
#595
b100100010 .
1$
#596
0$
#597
b100100011 .
1$
#598
0$
#599
b100100100 .
1$
#600
0$
#601
b100100101 .
1$
#602
0$
#603
b100100110 .
1$
#604
0$
#605
b100100111 .
1$
#606
0$
#607
b100101000 .
1$
#608
0$
#609
b100101001 .
1$
#610
0$
#611
b100101010 .
1$
#612
0$
#613
b100101011 .
1$
#614
0$
#615
b100101100 .
1$
#616
0$
#617
b100101101 .
1$
#618
0$
#619
b100101110 .
1$
#620
0$
#621
b100101111 .
1$
#622
0$
#623
b100110000 .
1$
#624
0$
#625
b100110001 .
1$
#626
0$
#627
b100110010 .
1$
#628
0$
#629
b100110011 .
1$
#630
0$
#631
b100110100 .
1$
#632
0$
#633
b100110101 .
1$
#634
0$
#635
b100110110 .
1$
#636
0$
#637
b100110111 .
1$
#638
0$
#639
b100111000 .
1$
#640
0$
#641
b100111001 .
1$
#642
0$
#643
b100111010 .
1$
#644
0$
#645
b100111011 .
1$
#646
0$
#647
b100111100 .
1$
#648
0$
#649
b100111101 .
1$
#650
0$
#651
b100111110 .
1$
#652
0$
#653
b100111111 .
1$
#654
0$
#655
b101000000 .
1$
#656
0$
#657
b101000001 .
1$
#658
0$
#659
b101000010 .
1$
#660
0$
#661
b101000011 .
1$
#662
0$
#663
b101000100 .
1$
#664
0$
#665
b101000101 .
1$
#666
0$
#667
b101000110 .
1$
#668
0$
#669
b101000111 .
1$
#670
0$
#671
b101001000 .
1$
#672
0$
#673
b101001001 .
1$
#674
0$
#675
b101001010 .
1$
#676
0$
#677
b101001011 .
1$
#678
0$
#679
b101001100 .
1$
#680
0$
#681
b101001101 .
1$
#682
0$
#683
b101001110 .
1$
#684
0$
#685
b101001111 .
1$
#686
0$
#687
b101010000 .
1$
#688
0$
#689
b101010001 .
1$
#690
0$
#691
b101010010 .
1$
#692
0$
#693
b101010011 .
1$
#694
0$
#695
b101010100 .
1$
#696
0$
#697
b101010101 .
1$
#698
0$
#699
b101010110 .
1$
#700
0$
#701
b101010111 .
1$
#702
0$
#703
b101011000 .
1$
#704
0$
#705
b101011001 .
1$
#706
0$
#707
b101011010 .
1$
#708
0$
#709
b101011011 .
1$
#710
0$
#711
b101011100 .
1$
#712
0$
#713
b101011101 .
1$
#714
0$
#715
b101011110 .
1$
#716
0$
#717
b101011111 .
1$
#718
0$
#719
b101100000 .
1$
#720
0$
#721
b101100001 .
1$
#722
0$
#723
b101100010 .
1$
#724
0$
#725
b101100011 .
1$
#726
0$
#727
b101100100 .
1$
#728
0$
#729
b101100101 .
1$
#730
0$
#731
b101100110 .
1$
#732
0$
#733
b101100111 .
1$
#734
0$
#735
b101101000 .
1$
#736
0$
#737
b101101001 .
1$
#738
0$
#739
b101101010 .
1$
#740
0$
#741
b101101011 .
1$
#742
0$
#743
b101101100 .
1$
#744
0$
#745
b101101101 .
1$
#746
0$
#747
b101101110 .
1$
#748
0$
#749
b101101111 .
1$
#750
0$
#751
b101110000 .
1$
#752
0$
#753
b101110001 .
1$
#754
0$
#755
b101110010 .
1$
#756
0$
#757
b101110011 .
1$
#758
0$
#759
b101110100 .
1$
#760
0$
#761
b101110101 .
1$
#762
0$
#763
b101110110 .
1$
#764
0$
#765
b101110111 .
1$
#766
0$
#767
b101111000 .
1$
#768
0$
#769
b101111001 .
1$
#770
0$
#771
b101111010 .
1$
#772
0$
#773
b101111011 .
1$
#774
0$
#775
b101111100 .
1$
#776
0$
#777
b101111101 .
1$
#778
0$
#779
b101111110 .
1$
#780
0$
#781
b101111111 .
1$
#782
0$
#783
b110000000 .
1$
#784
0$
#785
b110000001 .
1$
#786
0$
#787
b110000010 .
1$
#788
0$
#789
b110000011 .
1$
#790
0$
#791
b110000100 .
1$
#792
0$
#793
b110000101 .
1$
#794
0$
#795
b110000110 .
1$
#796
0$
#797
b110000111 .
1$
#798
0$
#799
b110001000 .
1$
#800
0$
#801
b110001001 .
1$
#802
0$
#803
b110001010 .
1$
#804
0$
#805
b110001011 .
1$
#806
0$
#807
b110001100 .
1$
#808
0$
#809
b110001101 .
1$
#810
0$
#811
b110001110 .
1$
#812
0$
#813
b110001111 .
1$
#814
0$
#815
b110010000 .
1$
#816
0$
#817
b110010001 .
1$
#818
0$
#819
b110010010 .
1$
#820
0$
#821
b110010011 .
1$
#822
0$
#823
b110010100 .
1$
#824
0$
#825
b110010101 .
1$
#826
0$
#827
b110010110 .
1$
#828
0$
#829
b110010111 .
1$
#830
0$
#831
b110011000 .
1$
#832
0$
#833
b110011001 .
1$
#834
0$
#835
b110011010 .
1$
#836
0$
#837
b110011011 .
1$
#838
0$
#839
b110011100 .
1$
#840
0$
#841
b110011101 .
1$
#842
0$
#843
b110011110 .
1$
#844
0$
#845
b110011111 .
1$
#846
0$
#847
b110100000 .
1$
#848
0$
#849
b110100001 .
1$
#850
0$
#851
b110100010 .
1$
#852
0$
#853
b110100011 .
1$
#854
0$
#855
b110100100 .
1$
#856
0$
#857
b110100101 .
1$
#858
0$
#859
b110100110 .
1$
#860
0$
#861
b110100111 .
1$
#862
0$
#863
b110101000 .
1$
#864
0$
#865
b110101001 .
1$
#866
0$
#867
b110101010 .
1$
#868
0$
#869
b110101011 .
1$
#870
0$
#871
b110101100 .
1$
#872
0$
#873
b110101101 .
1$
#874
0$
#875
b110101110 .
1$
#876
0$
#877
b110101111 .
1$
#878
0$
#879
b110110000 .
1$
#880
0$
#881
b110110001 .
1$
#882
0$
#883
b110110010 .
1$
#884
0$
#885
b110110011 .
1$
#886
0$
#887
b110110100 .
1$
#888
0$
#889
b110110101 .
1$
#890
0$
#891
b110110110 .
1$
#892
0$
#893
b110110111 .
1$
#894
0$
#895
b110111000 .
1$
#896
0$
#897
b110111001 .
1$
#898
0$
#899
b110111010 .
1$
#900
0$
#901
b110111011 .
1$
#902
0$
#903
b110111100 .
1$
#904
0$
#905
b110111101 .
1$
#906
0$
#907
b110111110 .
1$
#908
0$
#909
b110111111 .
1$
#910
0$
#911
b111000000 .
1$
#912
0$
#913
b111000001 .
1$
#914
0$
#915
b111000010 .
1$
#916
0$
#917
b111000011 .
1$
#918
0$
#919
b111000100 .
1$
#920
0$
#921
b111000101 .
1$
#922
0$
#923
b111000110 .
1$
#924
0$
#925
b111000111 .
1$
#926
0$
#927
b111001000 .
1$
#928
0$
#929
b111001001 .
1$
#930
0$
#931
b111001010 .
1$
#932
0$
#933
b111001011 .
1$
#934
0$
#935
b111001100 .
1$
#936
0$
#937
b111001101 .
1$
#938
0$
#939
b111001110 .
1$
#940
0$
#941
b111001111 .
1$
#942
0$
#943
b111010000 .
1$
#944
0$
#945
b111010001 .
1$
#946
0$
#947
b111010010 .
1$
#948
0$
#949
b111010011 .
1$
#950
0$
#951
b111010100 .
1$
#952
0$
#953
b111010101 .
1$
#954
0$
#955
b111010110 .
1$
#956
0$
#957
b111010111 .
1$
#958
0$
#959
b111011000 .
1$
#960
0$
#961
b111011001 .
1$
#962
0$
#963
b111011010 .
1$
#964
0$
#965
b111011011 .
1$
#966
0$
#967
b111011100 .
1$
#968
0$
#969
b111011101 .
1$
#970
0$
#971
b111011110 .
1$
#972
0$
#973
b111011111 .
1$
#974
0$
#975
b111100000 .
1$
#976
0$
#977
b111100001 .
1$
#978
0$
#979
b111100010 .
1$
#980
0$
#981
b111100011 .
1$
#982
0$
#983
b111100100 .
1$
#984
0$
#985
b111100101 .
1$
#986
0$
#987
b111100110 .
1$
#988
0$
#989
b111100111 .
1$
#990
0$
#991
b111101000 .
1$
#992
0$
#993
b111101001 .
1$
#994
0$
#995
b111101010 .
1$
#996
0$
#997
b111101011 .
1$
#998
0$
#999
b111101100 .
1$
#1000
0$
#1001
b111101101 .
1$
#1002
0$
#1003
b111101110 .
1$
#1004
0$
#1005
b111101111 .
1$
#1006
0$
#1007
b111110000 .
1$
#1008
0$
#1009
b111110001 .
1$
#1010
0$
#1011
b111110010 .
1$
#1012
0$
#1013
b111110011 .
1$
#1014
0$
#1015
b111110100 .
1$
#1016
0$
#1017
b111110101 .
1$
#1018
0$
#1019
b111110110 .
1$
#1020
0$
#1021
b111110111 .
1$
#1022
0$
#1023
b111111000 .
1$
#1024
0$
#1025
b111111001 .
1$
#1026
0$
#1027
b111111010 .
1$
#1028
0$
#1029
b111111011 .
1$
#1030
0$
#1031
b111111100 .
1$
#1032
0$
#1033
b111111101 .
1$
#1034
0$
#1035
b111111110 .
1$
#1036
0$
#1037
b111111111 .
1$
#1038
0$
#1039
b1000000000 .
1$
#1040
0$
#1041
b1000000001 .
1$
#1042
0$
#1043
b1000000010 .
1$
#1044
0$
#1045
b1000000011 .
1$
#1046
0$
#1047
b1000000100 .
1$
#1048
0$
#1049
b1000000101 .
1$
#1050
0$
#1051
b1000000110 .
1$
#1052
0$
#1053
b1000000111 .
1$
#1054
0$
#1055
b1000001000 .
1$
#1056
0$
#1057
b1000001001 .
1$
#1058
0$
#1059
b1000001010 .
1$
#1060
0$
#1061
b1000001011 .
1$
#1062
0$
#1063
b1000001100 .
1$
#1064
0$
#1065
b1000001101 .
1$
#1066
0$
#1067
b1000001110 .
1$
#1068
0$
#1069
b1000001111 .
1$
#1070
0$
#1071
b1000010000 .
1$
#1072
0$
#1073
b1000010001 .
1$
#1074
0$
#1075
b1000010010 .
1$
#1076
0$
#1077
b1000010011 .
1$
#1078
0$
#1079
b1000010100 .
1$
#1080
0$
#1081
b1000010101 .
1$
#1082
0$
#1083
b1000010110 .
1$
#1084
0$
#1085
b1000010111 .
1$
#1086
0$
#1087
b1000011000 .
1$
#1088
0$
#1089
b1000011001 .
1$
#1090
0$
#1091
b1000011010 .
1$
#1092
0$
#1093
b1000011011 .
1$
#1094
0$
#1095
b1000011100 .
1$
#1096
0$
#1097
b1000011101 .
1$
#1098
0$
#1099
b1000011110 .
1$
#1100
0$
#1101
b1000011111 .
1$
#1102
0$
#1103
b1000100000 .
1$
#1104
0$
#1105
b1000100001 .
1$
#1106
0$
#1107
b1000100010 .
1$
#1108
0$
#1109
b1000100011 .
1$
#1110
0$
#1111
b1000100100 .
1$
#1112
0$
#1113
b1000100101 .
1$
#1114
0$
#1115
b1000100110 .
1$
#1116
0$
#1117
b1000100111 .
1$
#1118
0$
#1119
b1000101000 .
1$
#1120
0$
#1121
b1000101001 .
1$
#1122
0$
#1123
b1000101010 .
1$
#1124
0$
#1125
b1000101011 .
1$
#1126
0$
#1127
b1000101100 .
1$
#1128
0$
#1129
b1000101101 .
1$
#1130
0$
#1131
b1000101110 .
1$
#1132
0$
#1133
b1000101111 .
1$
#1134
0$
#1135
b1000110000 .
1$
#1136
0$
#1137
b1000110001 .
1$
#1138
0$
#1139
b1000110010 .
1$
#1140
0$
#1141
b1000110011 .
1$
#1142
0$
#1143
b1000110100 .
1$
#1144
0$
#1145
b1000110101 .
1$
#1146
0$
#1147
b1000110110 .
1$
#1148
0$
#1149
b1000110111 .
1$
#1150
0$
#1151
b1000111000 .
1$
#1152
0$
#1153
b1000111001 .
1$
#1154
0$
#1155
b1000111010 .
1$
#1156
0$
#1157
b1000111011 .
1$
#1158
0$
#1159
b1000111100 .
1$
#1160
0$
#1161
b1000111101 .
1$
#1162
0$
#1163
b1000111110 .
1$
#1164
0$
#1165
b1000111111 .
1$
#1166
0$
#1167
b1001000000 .
1$
#1168
0$
#1169
b1001000001 .
1$
#1170
0$
#1171
b1001000010 .
1$
#1172
0$
#1173
b1001000011 .
1$
#1174
0$
#1175
b1001000100 .
1$
#1176
0$
#1177
b1001000101 .
1$
#1178
0$
#1179
b1001000110 .
1$
#1180
0$
#1181
b1001000111 .
1$
#1182
0$
#1183
b1001001000 .
1$
#1184
0$
#1185
b1001001001 .
1$
#1186
0$
#1187
b1001001010 .
1$
#1188
0$
#1189
b1001001011 .
1$
#1190
0$
#1191
b1001001100 .
1$
#1192
0$
#1193
b1001001101 .
1$
#1194
0$
#1195
b1001001110 .
1$
#1196
0$
#1197
b1001001111 .
1$
#1198
0$
#1199
b1001010000 .
1$
#1200
0$
#1201
b1001010001 .
1$
#1202
0$
#1203
b1001010010 .
1$
#1204
0$
#1205
b1001010011 .
1$
#1206
0$
#1207
b1001010100 .
1$
#1208
0$
#1209
b1001010101 .
1$
#1210
0$
#1211
b1001010110 .
1$
#1212
0$
#1213
b1001010111 .
1$
#1214
0$
#1215
b1001011000 .
1$
#1216
0$
#1217
b1001011001 .
1$
#1218
0$
#1219
b1001011010 .
1$
#1220
0$
#1221
b1001011011 .
1$
#1222
0$
#1223
b1001011100 .
1$
#1224
0$
#1225
b1001011101 .
1$
#1226
0$
#1227
b1001011110 .
1$
#1228
0$
#1229
b1001011111 .
1$
#1230
0$
#1231
b1001100000 .
1$
#1232
0$
#1233
b1001100001 .
1$
#1234
0$
#1235
b1001100010 .
1$
#1236
0$
#1237
b1001100011 .
1$
#1238
0$
#1239
b1001100100 .
1$
#1240
0$
#1241
b1001100101 .
1$
#1242
0$
#1243
b1001100110 .
1$
#1244
0$
#1245
b1001100111 .
1$
#1246
0$
#1247
b1001101000 .
1$
#1248
0$
#1249
b1001101001 .
1$
#1250
0$
#1251
b1001101010 .
1$
#1252
0$
#1253
b1001101011 .
1$
#1254
0$
#1255
b1001101100 .
1$
#1256
0$
#1257
b1001101101 .
1$
#1258
0$
#1259
b1001101110 .
1$
#1260
0$
#1261
b1001101111 .
1$
#1262
0$
#1263
b1001110000 .
1$
#1264
0$
#1265
b1001110001 .
1$
#1266
0$
