Lab 1/full_add.v
module full_add ( 
    input a, b, cin,
    output sum, cout );

// write code here

wire a_and_b, a_xor_b, a_xor_b_and_cin;
assign a_and_b = a & b;
assign a_xor_b = a ^ b;
assign a_xor_b_and_cin = a_xor_b & cin;

assign cout = a_and_b ^ a_xor_b_and_cin;
assign sum = a_xor_b ^ cin;

endmodule

Lab 1/full_add_3b.v
module full_add_3b( 
    input [2:0] a, b,
    input cin,
    output [2:0] cout,
    output [2:0] sum );

	// write code here

    full_add add1(
        .a(a[0]),
        .b(b[0]),
        .cin(cin),
        .cout(cout[0]),
        .sum(sum[0])
    );
    full_add add2(
        .a(a[1]),
        .b(b[1]),
        .cin(cout[0]),
        .cout(cout[1]),
        .sum(sum[1])
    );
    full_add add3(
        .a(a[2]),
        .b(b[2]),
        .cin(cout[1]),
        .cout(cout[2]),
        .sum(sum[2])
    );

    // assign sum = a +b +cin;
    // assign cout[0] = (a[0] & b[0]) | (a[0] & cin) | (b[0] & cin);
    // assign cout[1] = (a[1] & b[1]) | (a[1] & cout[0]) | (b[1] & cout[0]);
    // assign cout[2] = (a[2] & b[2]) | (a[2] & cout[1]) | (b[2] & cout[1]);
    
endmodule

Lab 1/full_add_3b_tb.v
`timescale 1ns/100ps // 1 ns time unit, 100 ps resolution

module full_add_3b_tb;

	reg [2:0] a = 0, b = 0;
	reg carry = 0;
	wire [2:0] sum, carry_out;

	full_add_3b full_add_mod0
	(
		.a(a),
		.b(b),
		.cin(carry),
		.cout(carry_out),
		.sum(sum)
	);

	initial begin
		$dumpfile("wave.vcd");		// create a VCD waveform dump called "wave.vcd"
		$dumpvars(0, full_add_3b_tb);		// dump variable changes in the testbench
									// and all modules under it

		#5 a = 2; b = 3; 
		#5 carry = 1;
		#5 b = 2; carry = 0;
		#5 a = 0; b = 0; carry = 1;
		#5 b = 4;
		#5 a = 6; b = 1;
		#5 a = 0; b = 6;
		#5 a = 6; b = 2;
		#5 a = 1; b = 1; carry = 0;
		#5 a = 0; b = 0; carry = 1;
		#5 b = 6;
		#5 a = 7; b = 3; carry = 0;


	
		$finish();
	end

	initial begin
		$monitor("t=%-4d: cout = %d, sum = %d", $time, carry_out, sum);
	end
endmodule

Lab 1/out/wave.vcd
$date
	Wed Oct  9 15:22:00 2024
$end
$version
	Icarus Verilog
$end
$timescale
	100ps
$end
$scope module full_add_3b_tb $end
$var wire 3 ! sum [2:0] $end
$var wire 3 " carry_out [2:0] $end
$var reg 3 # a [2:0] $end
$var reg 3 $ b [2:0] $end
$var reg 1 % carry $end
$scope module full_add_mod0 $end
$var wire 3 & a [2:0] $end
$var wire 3 ' b [2:0] $end
$var wire 1 % cin $end
$var wire 3 ( sum [2:0] $end
$var wire 3 ) cout [2:0] $end
$scope module add1 $end
$var wire 1 * a $end
$var wire 1 + a_and_b $end
$var wire 1 , a_xor_b $end
$var wire 1 - a_xor_b_and_cin $end
$var wire 1 . b $end
$var wire 1 % cin $end
$var wire 1 / cout $end
$var wire 1 0 sum $end
$upscope $end
$scope module add2 $end
$var wire 1 1 a $end
$var wire 1 2 a_and_b $end
$var wire 1 3 a_xor_b $end
$var wire 1 4 a_xor_b_and_cin $end
$var wire 1 5 b $end
$var wire 1 6 cin $end
$var wire 1 7 cout $end
$var wire 1 8 sum $end
$upscope $end
$scope module add3 $end
$var wire 1 9 a $end
$var wire 1 : a_and_b $end
$var wire 1 ; a_xor_b $end
$var wire 1 < a_xor_b_and_cin $end
$var wire 1 = b $end
$var wire 1 > cin $end
$var wire 1 ? cout $end
$var wire 1 @ sum $end
$upscope $end
$upscope $end
$upscope $end
$enddefinitions $end
$comment Show the parameter values. $end
$dumpall
$end
#0
$dumpvars
0@
0?
0>
0=
0<
0;
0:
09
08
07
06
05
04
03
02
01
00
0/
0.
0-
0,
0+
0*
b0 )
b0 (
b0 '
b0 &
0%
b0 $
b0 #
b0 "
b0 !
$end
#50
1@
1>
b101 !
b101 (
10
b10 "
b10 )
17
1,
12
1.
15
11
b11 $
b11 '
b10 #
b10 &
#100
18
16
b11 "
b11 )
1/
1-
b110 !
b110 (
00
1%
#150
08
06
b10 "
b10 )
0/
0,
0-
b100 !
b100 (
00
0.
0%
b10 $
b10 '
#200
0@
0>
b0 "
b0 )
07
02
b1 !
b1 (
10
05
01
1%
b0 $
b0 '
b0 #
b0 &
#250
b101 !
b101 (
1@
1;
1=
b100 $
b100 '
#300
1?
1<
0@
1>
17
14
16
b111 "
b111 )
1/
1-
00
b0 !
b0 (
08
1,
13
1.
0=
11
19
b1 $
b1 '
b110 #
b110 &
#350
0?
0<
1@
0>
07
04
18
06
b0 "
b0 )
0/
0-
b111 !
b111 (
10
0,
0.
15
1=
01
09
b110 $
b110 '
b0 #
b0 &
#400
1?
1<
0@
1>
b110 "
b110 )
17
b1 !
b1 (
08
12
03
0=
11
19
b10 $
b10 '
b110 #
b110 &
#450
18
16
0>
0?
1/
b1 "
b1 )
07
0<
0@
1+
02
0;
b10 !
b10 (
00
1.
05
1*
01
09
0%
b1 $
b1 '
b1 #
b1 &
#500
08
06
b0 "
b0 )
0/
0+
b1 !
b1 (
10
0.
0*
1%
b0 $
b0 '
b0 #
b0 &
#550
18
b111 !
b111 (
1@
13
1;
15
1=
b110 $
b110 '
#600
1?
1<
0@
16
1>
1/
b111 "
b111 )
17
18
1+
12
03
b10 !
b10 (
00
1.
0=
1*
11
19
0%
b11 $
b11 '
b111 #
b111 &
